opusFC.cp311-win_amd64.pyd
opusfc-1.5.0.dist-info/licenses/LICENSE
opusfc-1.5.0.dist-info/METADATA
opusfc-1.5.0.dist-info/WHEEL
opusfc-1.5.0.dist-info/top_level.txt
opusfc-1.5.0.dist-info/RECORD
