Metadata-Version: 2.4
Name: opusFC
Version: 1.5.0
Summary: OPUS File Converter module
Author-email: Stuart Read <stuart.read@lightsource.ca>
License: MIT
Classifier: Development Status :: 5 - Production/Stable
Classifier: Intended Audience :: Developers
Classifier: Intended Audience :: Science/Research
Classifier: Programming Language :: Python :: 3
Requires-Python: >=3.9
License-File: LICENSE
Requires-Dist: numpy
Dynamic: license-file
